mypackage/__init__.py
mypackage/main.py
kfaction-0.0.3.dist-info/METADATA
kfaction-0.0.3.dist-info/WHEEL
kfaction-0.0.3.dist-info/top_level.txt
kfaction-0.0.3.dist-info/RECORD
