Metadata-Version: 2.1
Name: kfaction
Version: 0.0.3
Summary: Nouveau bypass pour kfaction
Home-page: https://github.com/pypa/sampleproject
Author: kAZEN Donovan
Author-email: kazendonovan@gmail.com
Project-URL: Bug Tracker, https://github.com/pypa/sampleproject/issues
Classifier: Programming Language :: Python :: 3
Classifier: License :: OSI Approved :: MIT License
Classifier: Operating System :: OS Independent
Requires-Python: >=3.6
